tinboard/__init__.py
tinboard/__main__.py
tinboard/app.py
tinboard/py.typed
tinboard/commands/__init__.py
tinboard/commands/bookmarks.py
tinboard/commands/core_commands.py
tinboard/commands/core_filters.py
tinboard/commands/tags.py
tinboard/data/__init__.py
tinboard/data/bookmarks.py
tinboard/data/config.py
tinboard/data/exit_states.py
tinboard/data/locations.py
tinboard/data/token.py
tinboard/messages/__init__.py
tinboard/messages/commands.py
tinboard/messages/tags.py
tinboard/pinboard/__init__.py
tinboard/pinboard/api.py
tinboard/pinboard/bookmark_data.py
tinboard/pinboard/parse_time.py
tinboard/screens/__init__.py
tinboard/screens/bookmark_input.py
tinboard/screens/confirm.py
tinboard/screens/help.py
tinboard/screens/main.py
tinboard/screens/search_input.py
tinboard/screens/settings.py
tinboard/screens/token_input.py
tinboard/screens/wayback_checker.py
tinboard/suggestions/__init__.py
tinboard/suggestions/tags.py
tinboard/wayback/__init__.py
tinboard/wayback/api.py
tinboard/widgets/__init__.py
tinboard/widgets/bookmarks.py
tinboard/widgets/details.py
tinboard/widgets/extended_option_list.py
tinboard/widgets/filters.py
tinboard/widgets/tags.py
tinboard-0.15.1.dist-info/METADATA
tinboard-0.15.1.dist-info/WHEEL
tinboard-0.15.1.dist-info/entry_points.txt
tinboard-0.15.1.dist-info/top_level.txt
tinboard-0.15.1.dist-info/RECORD
