Metadata-Version: 2.1
Name: tinboard
Version: 0.15.1
Summary: A Pinboard client for the terminal
Home-page: https://github.com/davep/tinboard
Author: Dave Pearson
Author-email: davep@davep.org
Maintainer: Dave Pearson
Maintainer-email: davep@davep.org
License: License :: OSI Approved :: GNU General Public License v3 or later (GPLv3+)
Project-URL: Documentation, https://github.com/davep/tinboard/blob/main/README.md
Project-URL: Source, https://github.com/davep/tinboard
Project-URL: Issues, https://github.com/davep/tinboard/issues
Project-URL: Discussions, https://github.com/davep/tinboard/discussions
Keywords: bookmark,pinboard,terminal
Classifier: License :: OSI Approved :: GNU General Public License v3 or later (GPLv3+)
Classifier: Environment :: Console
Classifier: Development Status :: 5 - Production/Stable
Classifier: Intended Audience :: End Users/Desktop
Classifier: Operating System :: OS Independent
Classifier: Programming Language :: Python :: 3
Classifier: Programming Language :: Python :: 3 :: Only
Classifier: Programming Language :: Python :: 3.10
Classifier: Programming Language :: Python :: 3.11
Classifier: Programming Language :: Python :: 3.12
Classifier: Topic :: Education
Classifier: Topic :: Internet
Classifier: Topic :: Terminals
Classifier: Topic :: Utilities
Classifier: Typing :: Typed
Requires-Python: <3.13,>=3.10
Requires-Dist: textual ==0.70.0
Requires-Dist: xdg-base-dirs >=6.0.0
Requires-Dist: pytz
Requires-Dist: humanize >=4.8.0
Requires-Dist: httpx
Requires-Dist: pyperclip
